agptools/__init__.py
agptools/agptools.py
agptools/calls.py
agptools/colors.py
agptools/configurations.py
agptools/containers.py
agptools/crontab.py
agptools/files.py
agptools/helpers.py
agptools/loaders.py
agptools/logs.py
agptools/metrics.py
agptools/mutex.py
agptools/progress.py
agptools/web.py
agptools/cli/__init__.py
agptools/cli/config.py
agptools/cli/main.py
agptools/cli/wingdbstub.py
agptools/cli/workspace.py
agptools-0.1.357.dist-info/AUTHORS.rst
agptools-0.1.357.dist-info/LICENSE
agptools-0.1.357.dist-info/METADATA
agptools-0.1.357.dist-info/WHEEL
agptools-0.1.357.dist-info/entry_points.txt
agptools-0.1.357.dist-info/top_level.txt
agptools-0.1.357.dist-info/RECORD
