Metadata-Version: 2.2
Name: agptools
Version: 0.1.357
Summary: Minimal Tools not found in python library
Home-page: https://github.com/asterio/agptools
Author: Asterio Gonzalez
Author-email: asterio.gonzalez@gmail.com
License: MIT license
Keywords: agptools
Classifier: Development Status :: 2 - Pre-Alpha
Classifier: Intended Audience :: Developers
Classifier: License :: OSI Approved :: MIT License
Classifier: Natural Language :: English
Classifier: Programming Language :: Python :: 3
Classifier: Programming Language :: Python :: 3.9
Classifier: Programming Language :: Python :: 3.10
Classifier: Programming Language :: Python :: 3.11
Requires-Python: >=3.6
License-File: LICENSE
License-File: AUTHORS.rst
Requires-Dist: Click>=7.1.2
Requires-Dist: colorama
Requires-Dist: et-xmlfile
Requires-Dist: glom
Requires-Dist: lxml
Requires-Dist: python-dateutil
Requires-Dist: python-magic
Requires-Dist: pyyaml
Requires-Dist: shapely
Dynamic: author
Dynamic: author-email
Dynamic: classifier
Dynamic: description
Dynamic: home-page
Dynamic: keywords
Dynamic: license
Dynamic: requires-dist
Dynamic: requires-python
Dynamic: summary
